lattices/__init__.py
lattices/constraints.py
lattices/lattice.py
lattices/lattices.py
lattices/orderings.py
lattices/utils.py
lattices-0.3.5.dist-info/LICENSE.txt
lattices-0.3.5.dist-info/WHEEL
lattices-0.3.5.dist-info/METADATA
lattices-0.3.5.dist-info/RECORD
