Metadata-Version: 1.1
Name: lattices
Version: 0.3.5
Summary: Lattices is a package for the construction of lattices from a set of nodes and
Home-page: https://github.com/dit/lattices
Author: Ryan G. James
Author-email: ryangregoryjames@gmail.com
